boto3_retry.py
boto3_retry-0.1.2.dist-info/top_level.txt
boto3_retry-0.1.2.dist-info/METADATA
boto3_retry-0.1.2.dist-info/DESCRIPTION.rst
boto3_retry-0.1.2.dist-info/metadata.json
boto3_retry-0.1.2.dist-info/WHEEL
boto3_retry-0.1.2.dist-info/RECORD
