Metadata-Version: 2.0
Name: boto3-retry
Version: 0.1.2
Summary: A tool for easily retring failed AWS requests via boto3 based on the error code
Home-page: https://github.com/timmmartin19/boto3_retry
Author: Tim Martin
Author-email: tim@timmartin.me
License: MIT license
Keywords: boto3_retry
Platform: UNKNOWN
Classifier: Development Status :: 2 - Pre-Alpha
Classifier: Intended Audience :: Developers
Classifier: License :: OSI Approved :: MIT License
Classifier: Natural Language :: English
Classifier: Programming Language :: Python :: 3
Classifier: Programming Language :: Python :: 3.4
Classifier: Programming Language :: Python :: 3.5
Requires-Dist: boto3
Requires-Dist: retrying
Requires-Dist: wrapt
